Figure_square.py
figure_square-0.0.3.dist-info/METADATA
figure_square-0.0.3.dist-info/WHEEL
figure_square-0.0.3.dist-info/top_level.txt
figure_square-0.0.3.dist-info/RECORD
